Metadata-Version: 2.1
Name: pybarycuda
Version: 1.0.0
Summary: A tiny CUDA library for fast barycentric operations
Home-page: https://github.com/postmalloc/barycuda
Author: Srimukh Sripada
Author-email: hi@srimukh.com
License: MIT
Platform: UNKNOWN
